helga_quest/__init__.py
helga_quest/core.py
helga_quest/driver.py
helga_quest/plugin.py
helga_quest/util.py
helga_quest-1.1.0.dist-info/DESCRIPTION.rst
helga_quest-1.1.0.dist-info/METADATA
helga_quest-1.1.0.dist-info/RECORD
helga_quest-1.1.0.dist-info/WHEEL
helga_quest-1.1.0.dist-info/entry_points.txt
helga_quest-1.1.0.dist-info/metadata.json
helga_quest-1.1.0.dist-info/top_level.txt
helga_quest-1.1.0.dist-info/zip-safe
tests/__init__.py
tests/test_core.py
