Metadata-Version: 2.0
Name: helga-quest
Version: 1.1.0
Summary: Collaborative RPG consisting of user driven content
Home-page: https://github.com/narfman0/helga-quest
Author: Jon Robison
Author-email: narfman0@gmail.com
License: LICENSE
Keywords: irc bot quest
Platform: UNKNOWN
Classifier: Development Status :: 4 - Beta
Classifier: Topic :: Communications :: Chat :: Internet Relay Chat
Classifier: License :: OSI Approved :: GNU General Public License v3 (GPLv3)
Classifier: Operating System :: OS Independent
Classifier: Programming Language :: Python
Classifier: Topic :: Software Development :: Libraries :: Python Modules
Classifier: Topic :: Communications :: Chat :: Internet Relay Chat
Requires-Dist: helga
Requires-Dist: jaraco.modb
